promg/__init__.py
promg/cypher_queries/__init__.py
promg/cypher_queries/data_importer_ql.py
promg/cypher_queries/db_managment_ql.py
promg/cypher_queries/exporter_ql.py
promg/cypher_queries/inference_engine_ql.py
promg/cypher_queries/process_discovery_ql.py
promg/cypher_queries/semantic_header_ql.py
promg/cypher_queries/task_identification_ql.py
promg/data_managers/__init__.py
promg/data_managers/datastructures.py
promg/data_managers/properties.py
promg/data_managers/semantic_header.py
promg/database_managers/__init__.py
promg/database_managers/authentication.py
promg/database_managers/custom_exceptions.py
promg/database_managers/db_connection.py
promg/database_managers/remote_authentication.py
promg/database_managers/models/__init__.py
promg/database_managers/models/query.py
promg/facades/__init__.py
promg/facades/oced_pg.py
promg/modules/__init__.py
promg/modules/data_importer.py
promg/modules/db_management.py
promg/modules/ekg_builder_semantic_header.py
promg/modules/exporter.py
promg/modules/inference_engine.py
promg/modules/process_discovery.py
promg/modules/task_identification.py
promg/utilities/__init__.py
promg/utilities/auxiliary_functions.py
promg/utilities/configuration.py
promg/utilities/context_manager_tqdm.py
promg/utilities/get_db_size.py
promg/utilities/performance_handling.py
promg/utilities/singleton.py
promg-2.4.6.dist-info/licenses/LICENSE
promg-2.4.6.dist-info/METADATA
promg-2.4.6.dist-info/WHEEL
promg-2.4.6.dist-info/top_level.txt
promg-2.4.6.dist-info/RECORD
