Metadata-Version: 2.4
Name: promg
Version: 2.4.6
Summary: Pyhton library to build Event Knowledge Graphs
Author: A. Swevels, D.Fahland
License: GPL 3.0
Requires-Python: >=3.7
License-File: LICENSE
Requires-Dist: neo4j
Requires-Dist: numpy
Requires-Dist: pandas
Requires-Dist: tabulate
Requires-Dist: tqdm
Requires-Dist: pyyaml
Dynamic: author
Dynamic: description
Dynamic: description-content-type
Dynamic: license
Dynamic: license-file
Dynamic: requires-dist
Dynamic: requires-python
Dynamic: summary
